seed_mcp/__init__.py
seed_mcp/home.hpi
seed_mcp/scoring_display.py
seed_mcp/seed_core.py
seed_mcp/seed_mcp.py
seed_mcp/publishing/__init__.py
seed_mcp/publishing/auto_redaction_workflow_v2.py
seed_mcp/publishing/publishing_pipeline.py
seed_mcp/publishing/redaction_manager.py
seed_mcp/publishing/seed_core.py
seed_mcp/publishing/seed_membership_site.py
seed_mcp/publishing/seed_quarantine_github_v2.py
seed_mcp/publishing/webserver_github.py
seed_mcp-0.1.1.dist-info/licenses/LICENSE
seed_mcp-0.1.1.dist-info/METADATA
seed_mcp-0.1.1.dist-info/WHEEL
seed_mcp-0.1.1.dist-info/entry_points.txt
seed_mcp-0.1.1.dist-info/top_level.txt
seed_mcp-0.1.1.dist-info/RECORD
