Metadata-Version: 2.4
Name: seed-mcp
Version: 0.1.1
Summary: SEED MCP - Unified System Identity and Publishing Platform for Compound Intelligence
Author-email: Isaac <isaac@sancovp.com>
License: GNOSYS Personal Builder License (GPBL) v1.0
Project-URL: Homepage, https://github.com/sancovp/seed-mcp
Project-URL: Repository, https://github.com/sancovp/seed-mcp
Requires-Python: >=3.8
License-File: LICENSE
Requires-Dist: fastmcp>=2.0.0
Requires-Dist: pydantic>=2.0.0
Requires-Dist: fastapi>=0.100.0
Requires-Dist: uvicorn>=0.23.0
Requires-Dist: requests>=2.31.0
Provides-Extra: dev
Requires-Dist: pytest; extra == "dev"
Requires-Dist: pytest-asyncio; extra == "dev"
Requires-Dist: mcp-use; extra == "dev"
Dynamic: license-file
Dynamic: requires-python
